Metadata-Version: 2.1
Name: manc
Version: 0.1.0
Summary: 一款可以接入自定义扩展的爬虫
Home-page: https://github.com/markadc/cman
Author: WangTuo
Author-email: markadc@126.com
License: MIT
Keywords: Python,Spider
Requires-Dist: requests
Requires-Dist: parsel
